Verilog_transpilers/Three_Inputs_And_Gate/three_and_gate.v
module and_gate (e1, e2, e3, s);
    input e1;
    input e2;
    input e3;
    output s;


    assign s = e1 & e2 & e3;

endmodule

Verilog_transpilers/Three_Inputs_And_Gate/three_test_and_gate.v
`timescale 1ns / 1ps
`include "three_and_gate.v"

module stimulus;
	// Inputs
	reg x;
	reg y;
	reg w;
	// Outputs
	wire z;
	// Instantiate the Unit Under Test (UUT)
	and_gate uut (
		x, 
		y, 
		w, 
		z
	);
 
	initial begin
	$dumpfile("test.vcd");
    $dumpvars(0,stimulus);
		// Initialize Inputs
		x = 0;
		y = 0;
		w = 0;
 
	#10 x = 1;
	#10 y = 1;
	#10 w = 1;
	#10 y = 0;
	#10 w = 0;	
	#10 x = 0;
	#10 y = 1;
	#10 w = 1;	  
	#40 ;
 
	end  
 
		initial begin
		 $monitor("t=%3d x=%d,y=%d,w=%d,z=%d \n",$time,x,y,w,z, );
		 end
 
endmodule

Verilog_transpilers/Three_Inputs_And_Gate/test.vcd
$date
	Fri Mar 17 11:47:43 2023
$end
$version
	Icarus Verilog
$end
$timescale
	1ps
$end
$scope module stimulus $end
$var wire 1 ! z $end
$var reg 1 " w $end
$var reg 1 # x $end
$var reg 1 $ y $end
$scope module uut $end
$var wire 1 # e1 $end
$var wire 1 $ e2 $end
$var wire 1 " e3 $end
$var wire 1 ! s $end
$upscope $end
$upscope $end
$enddefinitions $end
$comment Show the parameter values. $end
$dumpall
$end
#0
$dumpvars
0$
0#
0"
0!
$end
#10000
1#
#20000
1$
#30000
1!
1"
#40000
0!
0$
#50000
0"
#60000
0#
#70000
1$
#80000
1"
